waqiasync/__init__.py
waqiasync-1.1.0.dist-info/LICENSE
waqiasync-1.1.0.dist-info/METADATA
waqiasync-1.1.0.dist-info/WHEEL
waqiasync-1.1.0.dist-info/top_level.txt
waqiasync-1.1.0.dist-info/zip-safe
waqiasync-1.1.0.dist-info/RECORD
